src/funnSV/__init__.py
src/funnSV/annotation_sources/__init__.py
src/funnSV/annotation_sources/annotations_handler.py
src/funnSV/annotation_sources/transcriptome.py
src/funnSV/functional_analysis/__init__.py
src/funnSV/functional_analysis/structural_variants_functional_annotator.py
src/funnSV/funnSV_main.py
funnsv-0.0.2.dist-info/LICENSE.txt
funnsv-0.0.2.dist-info/METADATA
funnsv-0.0.2.dist-info/WHEEL
funnsv-0.0.2.dist-info/entry_points.txt
funnsv-0.0.2.dist-info/RECORD
