Metadata-Version: 2.1
Name: funnSV
Version: 0.0.2
Summary: Fast and effective functional annotation of SVs
License: MIT
Author: Nicolas Gaitan
Author-email: nicolas.gaitan@bsc.es
Requires-Python: >=3.7,<4.0
Classifier: Development Status :: 5 - Production/Stable
Classifier: Environment :: Console
Classifier: Intended Audience :: Science/Research
Classifier: License :: OSI Approved :: MIT License
Classifier: Operating System :: OS Independent
Classifier: Programming Language :: Python :: 3
Classifier: Programming Language :: Python :: 3.7
Classifier: Programming Language :: Python :: 3.8
Classifier: Programming Language :: Python :: 3.9
Classifier: Programming Language :: Python :: 3.10
Classifier: Programming Language :: Python :: 3.11
Classifier: Programming Language :: Python :: 3.12
Classifier: Topic :: Scientific/Engineering :: Bio-Informatics
Requires-Dist: pysam (>=0.21.0,<0.22.0)
Requires-Dist: variant-extractor
Project-URL: repository, https://github.com/ngaitan55/funnSV
